liar/__init__.py
liar/iamaliar.py
liar/iamprimitive.py
liar/iblurb.py
liar/igetraw.py
liar/ijusthelp.py
liar/ipictureit.py
liar/itransform.py
liar/images/animal/animals_amphibian_escuerzos.gif
liar/images/animal/animals_amphibian_flying_frog.gif
liar/images/animal/animals_amphibian_frog.gif
liar/images/animal/animals_amphibian_newt.gif
liar/images/animal/animals_amphibian_spotted_salamander.gif
liar/images/animal/animals_amphibian_three_toad_salamander.gif
liar/images/animal/animals_bird_albatross.gif
liar/images/animal/animals_bird_barbet.gif
liar/images/animal/animals_bird_bee_eater.gif
liar/images/animal/animals_bird_bird_of_paradise.gif
liar/images/animal/animals_bird_bittern.gif
liar/images/animal/animals_bird_bluebird.gif
liar/images/animal/animals_bird_boat_bill.gif
liar/images/animal/animals_bird_bower_bird.gif
liar/images/animal/animals_bird_broadbill.gif
liar/images/animal/animals_bird_broadtail.gif
liar/images/animal/animals_bird_budgie.gif
liar/images/animal/animals_bird_bullfinch.gif
liar/images/animal/animals_bird_bunting.gif
liar/images/animal/animals_bird_buzzard.gif
liar/images/animal/animals_bird_canary.gif
liar/images/animal/animals_bird_caracara.gif
liar/images/animal/animals_bird_cardinal.gif
liar/images/animal/animals_bird_cassowary.gif
liar/images/animal/animals_bird_chatterer.gif
liar/images/animal/animals_bird_chickadee.gif
liar/images/animal/animals_bird_chicken.gif
liar/images/animal/animals_bird_chiff_chaff.gif
liar/images/animal/animals_bird_chough.gif
liar/images/animal/animals_bird_cockatiel.gif
liar/images/animal/animals_bird_cockatoo.gif
liar/images/animal/animals_bird_coot.gif
liar/images/animal/animals_bird_crane.gif
liar/images/animal/animals_bird_crested_quail.gif
liar/images/animal/animals_bird_crossbill.gif
liar/images/animal/animals_bird_crow.gif
liar/images/animal/animals_bird_cuckoo.gif
liar/images/animal/animals_bird_curlew.gif
liar/images/animal/animals_bird_currasow.gif
liar/images/animal/animals_bird_darter.gif
elio_liar-1.0.dist-info/LICENSE
elio_liar-1.0.dist-info/METADATA
elio_liar-1.0.dist-info/WHEEL
elio_liar-1.0.dist-info/top_level.txt
elio_liar-1.0.dist-info/RECORD
